Metadata-Version: 2.1
Name: docker-compose-portenv
Version: 0.0.2
Summary: Reveal ports for Docker Compose containers
Home-page: https://github.com/nvllsvm/docker-compose-portenv
Author: Andrew Rabert
Author-email: ar@nullsum.net
License: UNKNOWN
Platform: UNKNOWN
